pysentinel/__init__.py
pysentinel/channels/__init__.py
pysentinel/channels/base.py
pysentinel/channels/channel_factory.py
pysentinel/channels/email.py
pysentinel/channels/slack.py
pysentinel/channels/telegram.py
pysentinel/channels/webhook.py
pysentinel/cli/__init__.py
pysentinel/cli/cli.py
pysentinel/config/__init__.py
pysentinel/config/loader.py
pysentinel/config/validator.py
pysentinel/core/__init__.py
pysentinel/core/scanner.py
pysentinel/core/scheduler.py
pysentinel/core/threshold.py
pysentinel/datasources/__init__.py
pysentinel/datasources/api.py
pysentinel/datasources/base.py
pysentinel/datasources/database.py
pysentinel/datasources/elasticsearch.py
pysentinel/datasources/prometheus.py
pysentinel/datasources/redis.py
pysentinel/datasources/stream.py
pysentinel/utils/__init__.py
pysentinel/utils/alert_db.py
pysentinel/utils/constants.py
pysentinel/utils/exception.py
pysentinel/utils/helper.py
pysentinel/utils/logging.py
pysentinel-0.1.5.dist-info/LICENSE
pysentinel-0.1.5.dist-info/METADATA
pysentinel-0.1.5.dist-info/WHEEL
pysentinel-0.1.5.dist-info/entry_points.txt
pysentinel-0.1.5.dist-info/RECORD
