Metadata-Version: 2.3
Name: pysentinel
Version: 0.1.5
Summary: A python package for threshold based alerting using simple configuration.
License: MIT
Author: Rakibul Haq
Author-email: haq.rakibul@gmail.com
Requires-Python: >=3.9,<4.0
Classifier: License :: OSI Approved :: MIT License
Classifier: Programming Language :: Python :: 3
Classifier: Programming Language :: Python :: 3.9
Classifier: Programming Language :: Python :: 3.10
Classifier: Programming Language :: Python :: 3.11
Classifier: Programming Language :: Python :: 3.12
Classifier: Programming Language :: Python :: 3.13
Requires-Dist: aiohttp (>=3.12.13,<4.0.0)
Requires-Dist: aioredis (>=2.0.1,<3.0.0)
Requires-Dist: elasticsearch (>=9.0.2,<10.0.0)
Requires-Dist: pyyaml (>=6.0.2,<7.0.0)
